{
  "zones": [
    {
      "name": "Scripts Zone",
      "paths": [
        "scripts/**/*"
      ],
      "belief": "Deployment and environment setup scripts for launching the Terminus client and the native Terminus backend.",
      "last_updated": "2026-03-18"
    },
    {
      "name": "Seed Zone",
      "paths": [
        "seed/**/*"
      ],
      "belief": "Coherence lab context injections, configuration presets, and toolset definitions imported directly into the user’s mind.",
      "last_updated": "2026-03-18"
    },
    {
      "name": "User Zone",
      "paths": [
        "user/**/*"
      ],
      "belief": "The active continuity footprint: contains persistent runtime state, conversation traces, dynamically loaded plugins, custom prompt pieces, and workspace databases.",
      "last_updated": "2026-03-18"
    },
    {
      "name": "Documentation",
      "paths": [
        "docs/**/*"
      ],
      "belief": "User-facing and internal documentation for this codebase.",
      "last_updated": "2026-03-18"
    }
  ]
}
